{"stats":{"minecraft:mined":{"minecraft:soul_sand":20,"minecraft:gravel":12},"minecraft:dropped":{"minecraft:gravel":2,"minecraft:acacia_boat":1,"minecraft:soul_sand":1,"minecraft:ender_pearl":114,"minecraft:nether_star":268,"minecraft:quartz_block":1,"minecraft:rabbit":5,"minecraft:ender_eye":54,"minecraft:chain_command_block":10,"minecraft:iron_shovel":4,"minecraft:ghast_tear":212,"minecraft:oak_sign":3},"minecraft:used":{"minecraft:glass":13,"minecraft:ender_eye":157,"minecraft:water_bucket":7,"minecraft:writable_book":1,"minecraft:iron_shovel":32,"minecraft:command_block":56,"minecraft:flint_and_steel":2,"minecraft:red_wool":23,"minecraft:oak_planks":4,"minecraft:lime_wool":45,"minecraft:redstone":25,"minecraft:oak_sign":48,"minecraft:stone_button":12,"minecraft:quartz_block":501,"minecraft:ender_pearl":3,"minecraft:chest":4,"minecraft:stone":26,"minecraft:redstone_block":3,"minecraft:gravel":63,"minecraft:player_head":22,"minecraft:bedrock":8,"minecraft:fishing_rod":620,"minecraft:torch":3,"minecraft:jungle_sign":1,"minecraft:sand":245,"minecraft:repeater":9,"minecraft:soul_sand":50,"minecraft:written_book":1,"minecraft:magenta_bed":1,"minecraft:chain_command_block":240,"minecraft:repeating_command_block":18,"minecraft:observer":7,"minecraft:obsidian":636,"minecraft:redstone_torch":25},"minecraft:picked_up":{"minecraft:ghast_tear":1,"minecraft:fishing_rod":1,"minecraft:chain_command_block":1,"minecraft:gravel":77,"minecraft:flint":1,"minecraft:stone_button":4,"minecraft:redstone":4,"minecraft:iron_axe":1,"minecraft:iron_shovel":2,"minecraft:oak_sign":10,"minecraft:ender_eye":62,"minecraft:redstone_torch":11,"minecraft:written_book":1,"minecraft:iron_pickaxe":1,"minecraft:soul_sand":84,"minecraft:nether_star":4,"minecraft:ender_pearl":16},"minecraft:custom":{"minecraft:time_since_rest":84063,"minecraft:sprint_one_cm":49319,"minecraft:damage_taken":310,"minecraft:walk_one_cm":409348,"minecraft:drop":636,"minecraft:damage_dealt":28,"minecraft:swim_one_cm":387,"minecraft:fly_one_cm":5933735,"minecraft:open_chest":33,"minecraft:crouch_one_cm":52781,"minecraft:play_one_minute":475585,"minecraft:deaths":2,"minecraft:sneak_time":25690,"minecraft:walk_under_water_one_cm":70681,"minecraft:jump":1859,"minecraft:leave_game":9,"minecraft:walk_on_water_one_cm":4345,"minecraft:time_since_death":84042,"minecraft:fall_one_cm":4045}},"DataVersion":2567}